arkane/__init__.py
arkane/common.py
arkane/commonTest.py
arkane/exceptions.py
arkane/explorer.py
arkane/explorerTest.py
arkane/input.py
arkane/inputTest.py
arkane/kinetics.py
arkane/kineticsTest.py
arkane/main.py
arkane/mainTest.py
arkane/modelchem.py
arkane/modelchemTest.py
arkane/output.py
arkane/outputTest.py
arkane/pdep.py
arkane/pdepTest.py
arkane/sensitivity.py
arkane/statmech.py
arkane/statmechTest.py
arkane/thermo.py
arkane/thermoTest.py
rmgpy/__init__.py
rmgpy/chemkinTest.py
rmgpy/constants.py
rmgpy/constantsTest.py
rmgpy/constraints.py
rmgpy/constraintsTest.py
rmgpy/display.py
rmgpy/exceptions.py
rmgpy/quantity.py
rmgpy/quantityTest.py
rmgpy/reaction.py
rmgpy/reactionTest.py
rmgpy/rmgobjectTest.py
rmgpy/species.py
rmgpy/speciesTest.py
rmgpy/stats.py
rmgpy/statsTest.py
rmgpy/transport.py
rmgpy/transportDataTest.py
rmgpy/util.py
rmgpy/version.py
rmgpy/yml.py
reactionmechanismgenerator-0.0.0a0.dist-info/LICENSE.txt
reactionmechanismgenerator-0.0.0a0.dist-info/METADATA
reactionmechanismgenerator-0.0.0a0.dist-info/WHEEL
reactionmechanismgenerator-0.0.0a0.dist-info/top_level.txt
reactionmechanismgenerator-0.0.0a0.dist-info/RECORD
