Metadata-Version: 2.1
Name: reactionmechanismgenerator
Version: 0.0.0a0
Summary: Reaction Mechanism Generator
Home-page: http://reactionmechanismgenerator.github.io
Author: William H. Green and the RMG Team
Author-email: rmg_dev@mit.edu
License-File: LICENSE.txt
